ckanext_dataset_series-0.1.1-py3.9-nspkg.pth
ckanext/dataset_series/__init__.py
ckanext/dataset_series/actions.py
ckanext/dataset_series/helpers.py
ckanext/dataset_series/plugin.py
ckanext/dataset_series/validators.py
ckanext/dataset_series/assets/script.js
ckanext/dataset_series/assets/style.css
ckanext/dataset_series/assets/webassets.yml
ckanext/dataset_series/public/.gitignore
ckanext/dataset_series/schemas/__init__.py
ckanext/dataset_series/schemas/dataset_in_series.yaml
ckanext/dataset_series/schemas/dataset_series.yaml
ckanext/dataset_series/schemas/dcat_ap_dataset_series.yaml
ckanext/dataset_series/schemas/presets.yaml
ckanext/dataset_series/templates/package/snippets/series_navigation.html
ckanext/dataset_series/tests/__init__.py
ckanext/dataset_series/tests/test_action.py
ckanext/dataset_series/tests/test_helpers.py
ckanext/dataset_series/tests/test_plugin.py
ckanext/dataset_series/tests/test_validators.py
ckanext_dataset_series-0.1.1.dist-info/licenses/LICENSE
ckanext_dataset_series-0.1.1.dist-info/METADATA
ckanext_dataset_series-0.1.1.dist-info/WHEEL
ckanext_dataset_series-0.1.1.dist-info/entry_points.txt
ckanext_dataset_series-0.1.1.dist-info/namespace_packages.txt
ckanext_dataset_series-0.1.1.dist-info/top_level.txt
ckanext_dataset_series-0.1.1.dist-info/RECORD
