Metadata-Version: 2.4
Name: ckanext-dataset-series
Version: 0.1.1
Summary: A fast and simple dataset series implementation for CKAN
Author: Adrià Mercader (amercader)
License: AGPL
Project-URL: Homepage, https://github.com/ckan/ckanext-dataset-series
Keywords: CKAN,DCAT,Dataset Series
Classifier: Development Status :: 4 - Beta
Classifier: License :: OSI Approved :: GNU Affero General Public License v3 or later (AGPLv3+)
Classifier: Programming Language :: Python :: 3.9
Classifier: Programming Language :: Python :: 3.10
Classifier: Programming Language :: Python :: 3.11
Classifier: Programming Language :: Python :: 3.12
License-File: LICENSE
Dynamic: license-file
